src/__init__.py
src/pinger.py
SystrayPinger-0.1.dist-info/top_level.txt
SystrayPinger-0.1.dist-info/METADATA
SystrayPinger-0.1.dist-info/DESCRIPTION.rst
SystrayPinger-0.1.dist-info/RECORD
SystrayPinger-0.1.dist-info/metadata.json
SystrayPinger-0.1.dist-info/WHEEL
