Metadata-Version: 2.0
Name: SystrayPinger
Version: 0.1
Summary: A ping tool that sits in your system tray
Home-page: http://github.com/zyphlar/pinger
Author: Will Bradley
Author-email: will@zyphon.com
License: GPL2
Keywords: pinging utility systray
Platform: UNKNOWN
